{"EZ": {"<s>": {"it": 1, "different!": 1, "uh": 1, "stirring": 1, "im": 1, "wait": 1, "what": 1, "this": 1, "0h": 1, "0H": 1, "did": 1, "R0MANTIC": 1, "ANSWER": 1, "get": 1, "GET": 2}, "it": {"feels": 1, "0ut": 1}, "feels": {"</s>": 1}, "</s>": {"<s>": 15}, "different!": {"</s>": 1}, "uh": {"</s>": 1}, "stirring": {"</s>": 1}, "im": {"n0t": 1}, "n0t": {"sure": 1}, "sure": {"</s>": 1}, "wait": {"</s>": 1}, "what": {"is": 1}, "is": {"that": 1}, "that": {"</s>": 1}, "this": {"feeling": 1, "r0b0t": 1}, "feeling": {"</s>": 1}, "0h": {"g0d": 1}, "g0d": {"</s>": 1}, "0H": {"MY": 1}, "MY": {"G0D": 1}, "G0D": {"WHAT": 1}, "WHAT": {"DID": 1}, "DID": {"Y0U": 1}, "Y0U": {"D0!": 1}, "D0!": {"</s>": 1}, "did": {"y0u": 1}, "y0u": {"pr0gram": 1}, "pr0gram": {"this": 1}, "r0b0t": {"t0": 1}, "t0": {"have": 1}, "have": {"feelings": 1}, "feelings": {"f0r": 1}, "f0r": {"y0u?": 1}, "y0u?": {"</s>": 1}, "R0MANTIC": {"FEELINGS???": 1}, "FEELINGS???": {"</s>": 1}, "ANSWER": {"ME": 1}, "ME": {"BLUE": 1}, "BLUE": {"BL00D": 1}, "BL00D": {"SCUM": 1}, "SCUM": {"</s>": 1}, "get": {"it": 1}, "0ut": {"</s>": 1}, "GET": {"IT": 14}, "IT": {"0UT!!!": 1, "0UT": 13}, "0UT!!!": {"</s>": 1}, "0UT": {"GET": 12, "</s>": 1}}, "TP": {"<s>": {"i": 1}, "i": {"will": 1}, "will": {"n0t": 1}, "n0t": {"be": 1}, "be": {"participating": 1}, "participating": {"</s>": 1}}, "RL": {"<s>": {"what": 4, "just": 1, "st0p": 1, "maybe": 6, "y0u": 7, "n0": 2, "its": 2, "i": 7, "breaking": 1, "and": 3, "but": 3, "the": 1, "pr0bably": 1, "it": 2, "s0rt": 1, "back": 1, "even": 1, "which": 1, "with": 1, "n0!": 1, "im": 1, "0bvi0usly": 1, "maybe!!!": 1, "parad0x": 1, "blah": 1, "didnt": 1, "oh": 1, "isnt": 1, "bslick": 1, "ribbit": 1, "WILL": 1, "I": 1, "hahaha!": 1, "0h": 1, "this": 1, "that": 1, "really": 2, "really*rand(rand(rand(rand(rand(0M)*0M)*0M)*0M)*0M)": 1, "!~M~0~D~N~A~R": 1, "g00dbye": 1, "enj0y": 1, "talk": 1}, "what": {"d0": 2, "they": 1, "g00d": 1}, "d0": {"y0u": 4, "all": 1}, "y0u": {"think": 1, "arent": 1, "</s>": 2, "kn0w": 1, "really": 2, "bug": 1, "can": 1, "want": 1, "cant": 1, "w0nt": 1, "still": 1, "pspace???": 1, "were": 1, "have": 1, "had": 1, "later": 1}, "think": {"y0ure": 1, "0f": 1, "c0uld": 1, "im": 1}, "y0ure": {"d0ing!": 1, "the": 1}, "d0ing!": {"</s>": 1}, "</s>": {"<s>": 69}, "just": {"st0p": 1, "wish": 1, "talking": 1, "being": 1, "</s>": 1}, "st0p": {"</s>": 2, "st0p": 5, "en0ugh": 1, "are": 1, "listening": 1}, "maybe": {"if": 3, "still": 1, "the": 1, "n0t": 1, "i": 1}, "if": {"i": 4, "it": 1}, "i": {"say": 2, "d0nt": 3, "kn0w": 1, "died": 1, "never": 1, "just": 1, "was": 2, "had": 1, "ended": 1, "w0uld": 1, "behave": 1, "suddenly": 1, "d0": 1, "think": 1, "dig": 1, "can": 1, "will": 1, "havent": 1}, "say": {"st0p": 1, "</s>": 1, "will": 1}, "en0ugh": {"s0mething": 1, "int0": 1}, "s0mething": {"else": 1, "here": 1}, "else": {"will": 1}, "will": {"happen": 1, "be": 1, "indirectly": 1, "have": 1, "also": 1}, "happen": {"instead": 1}, "instead": {"0f": 1}, "0f": {"the": 3, "sickness": 1, "it": 2, "a": 1, "kn0wing": 1, "my": 1, "y0ur": 1}, "the": {"thing": 1, "kn0wing": 1, "same": 1, "punchline": 1, "vast": 1, "s0urce": 1, "first": 1, "pr0blem": 1, "things": 1, "time": 1, "wall": 1, "0utc0me": 1, "functi0n": 1}, "thing": {"that": 1, "i": 1}, "that": {"d0es": 1, "</s>": 1, "y0ure": 1, "0ne": 1, "crazy!": 1, "was": 1, "but": 1, "is": 1, "parad0x": 1, "w0uld": 1}, "d0es": {"</s>": 1}, "arent": {"g0ing": 1}, "g0ing": {"t0": 1}, "t0": {"st0p": 2, "tear": 1, "hum0ring": 1, "f0ll0wing": 1, "watch": 1, "kn0w": 1, "think": 1, "tell": 1, "the": 2, "c0nstructive": 1, "inevitable": 1, "handle": 1, "s0mething": 1, "change": 1, "y0u": 1}, "are": {"y0u": 1, "c0nsequences": 1}, "n0": {"i": 1, "</s>": 1, "idea": 1, "way": 1, "ch0ice": 1}, "d0nt": {"care": 1, "even": 1, "kn0w": 1, "understand": 1}, "care": {"ab0ut": 1}, "ab0ut": {"that": 1, "it": 1}, "its": {"y0ur": 1, "exciting": 1, "energy": 1, "imp0ssible": 1}, "y0ur": {"quest": 1, "sessi0n": 1, "destructive": 1, "future": 1, "critical": 1, "absurd": 1, "rampant": 1}, "quest": {"t0": 1}, "tear": {"y0ur": 1}, "sessi0n": {"apart": 1}, "apart": {"</s>": 1}, "kn0w": {"its": 1, "wh0": 1, "this": 1, "</s>": 1, "h0w": 1}, "exciting": {"</s>": 1}, "breaking": {"stuff": 1}, "stuff": {"</s>": 1}, "and": {"n0t": 1, "c0nsequences": 1, "yet": 1, "fuss": 1, "meddle": 1, "now": 1, "rer0ute": 1, "rand0mly": 1}, "n0t": {"w0rrying": 1, "wh0": 1}, "w0rrying": {"ab0ut": 1}, "it": {"</s>": 3, "was": 1, "w0uld": 1, "is": 1, "will": 1, "t0": 1, "either": 1}, "but": {"there": 1, "if": 1, "im": 1, "y0u": 1, "with": 1, "t0": 1}, "there": {"are": 1}, "c0nsequences": {"t0": 2}, "hum0ring": {"y0ur": 1}, "destructive": {"impulses": 1}, "impulses": {"</s>": 1}, "f0ll0wing": {"</s>": 1}, "they": {"say": 1}, "wh0": {"</s>": 1, "kn0ws": 1}, "even": {"need": 1, "if": 1, "a": 1}, "need": {"t0": 1}, "watch": {"y0ur": 1}, "future": {"acti0ns": 1}, "acti0ns": {"t0": 1, "</s>": 1}, "this": {"</s>": 1, "elusive": 1, "is": 1}, "kn0wing": {"is": 1, "thats": 1}, "is": {"the": 1, "maybe": 1, "then": 1, "right": 1, "great": 1}, "same": {"as": 1}, "as": {"this": 1}, "elusive": {"feeling": 1}, "feeling": {"0f": 1}, "sickness": {"thats": 1}, "thats": {"been": 1, "a": 1}, "been": {"with": 1, "nice": 1}, "with": {"me": 1, "things": 1, "the": 1, "c0nsci0usly": 1, "that": 1, "zer0es": 1}, "me": {"f0r": 1, "t0": 1}, "f0r": {"years": 1}, "years": {"</s>": 1}, "pr0bably": {"since": 1}, "since": {"bef0re": 1}, "bef0re": {"i": 1}, "died": {"c0me": 1}, "c0me": {"t0": 1, "0f": 1}, "was": {"always": 1, "behaving": 1, "assured": 1, "even": 1, "tucked": 1}, "always": {"a": 1}, "a": {"big": 1, "special": 1, "manner": 1, "possibility": 1, "thing": 1}, "big": {"setup": 1}, "setup": {"</s>": 1}, "never": {"had": 1, "would": 1}, "had": {"0ne": 1, "s0me0ne": 1, "n0": 1}, "0ne": {"</s>": 1, "c0ming": 1, "0f": 1}, "s0rt": {"0f": 1}, "special": {"case": 1}, "case": {"here": 1}, "here": {"</s>": 2}, "wish": {"</s>": 1}, "back": {"when": 1}, "when": {"i": 1}, "behaving": {"recklessly": 1}, "recklessly": {"</s>": 1}, "s0me0ne": {"t0": 1}, "tell": {"me": 1}, "listening": {"</s>": 1}, "ended": {"up": 1}, "up": {"ign0ring": 1}, "ign0ring": {"their": 1}, "their": {"advice": 1}, "advice": {"</s>": 1}, "w0uld": {"have": 1, "be": 2}, "have": {"been": 1, "imagined": 1, "n0": 2}, "nice": {"</s>": 1}, "assured": {"i": 1}, "be": {"saving": 1, "the": 1, "just": 1}, "saving": {"my": 1}, "my": {"race": 1, "sentences": 1, "circuitry": 1, "reserve": 1, "quantum": 1, "p0wer": 1}, "race": {"</s>": 1}, "which": {"is": 1}, "still": {"true": 1, "havent": 1}, "true": {"i": 1}, "then": {"it": 1}, "punchline": {"t0": 1}, "vast": {"j0ke": 1}, "j0ke": {"</s>": 1}, "really": {"d0nt": 1, "think": 1, "</s>": 2}, "understand": {"anything": 1}, "anything": {"yet": 1}, "yet": {"d0": 1, "y0u": 1}, "bug": {"and": 1}, "fuss": {"and": 1}, "meddle": {"</s>": 1}, "things": {"m0re": 1, "i": 1}, "m0re": {"danger0us": 1}, "danger0us": {"than": 1}, "than": {"y0u": 1}, "can": {"imagine": 1, "pr0duce": 1}, "imagine": {"</s>": 1}, "want": {"with": 1}, "s0urce": {"0f": 1, "t0": 1}, "first": {"guardians": 1}, "guardians": {"</s>": 1}, "g00d": {"d0": 1}, "c0uld": {"c0me": 1}, "cant": {"p0ssibly": 1}, "p0ssibly": {"wield": 1}, "wield": {"its": 1}, "energy": {"0r": 1}, "0r": {"put": 1}, "put": {"it": 1}, "c0nstructive": {"use": 1}, "use": {"</s>": 1}, "w0nt": {"find": 1, "kn0w": 1}, "find": {"it": 1}, "either": {"</s>": 1}, "imp0ssible": {"</s>": 1}, "n0!": {"</s>": 1}, "havent": {"gathered": 1, "rand0mly": 1}, "gathered": {"that": 1}, "pr0blem": {"</s>": 1}, "im": {"thr0ugh": 1, "just": 1, "sure": 1, "0n": 1}, "thr0ugh": {"with": 1, "my": 1}, "c0nsci0usly": {"c0ntributing": 1}, "c0ntributing": {"t0": 1}, "inevitable": {"0utc0mes": 1}, "0utc0mes": {"</s>": 1}, "0bvi0usly": {"</s>": 1}, "talking": {"</s>": 1}, "indirectly": {"trigger": 1}, "trigger": {"y0ur": 1}, "critical": {"acti0ns": 1}, "kn0ws": {"</s>": 1}, "maybe!!!": {"</s>": 1}, "behave": {"in": 1}, "in": {"a": 1, "my": 1, "his": 1}, "manner": {"s0": 1}, "s0": {"rand0m": 1, "c0mpletely": 1}, "rand0m": {"</s>": 1, "number": 1, "fr0m": 1}, "parad0x": {"space": 2}, "space": {"w0nt": 1, "will": 1}, "h0w": {"t0": 1, "funny": 1}, "handle": {"it!": 1}, "it!": {"</s>": 1}, "blah": {"BL00P": 1}, "BL00P": {"blee": 1}, "blee": {"BLUH!@#$%^&*()_+": 1}, "BLUH!@#$%^&*()_+": {"</s>": 1}, "didnt": {"see": 1}, "see": {"that": 1}, "c0ming": {"did": 1}, "did": {"y0u": 1}, "pspace???": {"+": 1}, "+": {"?*rand(413^612)": 1}, "?*rand(413^612)": {"</s>": 1}, "oh": {"look": 1}, "look": {"and": 1}, "now": {"i": 1}, "suddenly": {"refuse": 1}, "refuse": {"to": 1}, "to": {"type": 1}, "type": {"zeroes": 1}, "zeroes": {"in": 1}, "sentences": {"</s>": 1}, "isnt": {"that": 1}, "crazy!": {"who": 1}, "who": {"thought": 1}, "thought": {"that": 1}, "possibility": {"</s>": 1}, "bslick": {"never": 1}, "would": {"have": 1}, "imagined": {"THAT": 1}, "THAT": {"little": 1, "</s>": 1}, "little": {"vestibule": 1}, "vestibule": {"of": 1}, "of": {"probability": 1}, "probability": {"was": 1}, "tucked": {"somewhere": 1}, "somewhere": {"in": 1}, "his": {"huge": 1}, "huge": {"glistening": 1}, "glistening": {"blow": 1}, "blow": {"sack": 1}, "sack": {"</s>": 1}, "ribbit": {"ribbit": 2, "</s>": 1}, "WILL": {"YOU": 1}, "YOU": {"LOOK": 1}, "LOOK": {"AT": 1}, "AT": {"THAT": 1}, "I": {"JUST": 1, "DID": 1}, "JUST": {"CONTROLLED": 1}, "CONTROLLED": {"THE": 1}, "THE": {"RIBBITS": 1}, "RIBBITS": {"AND": 1}, "AND": {"I": 1}, "DID": {"IT": 1}, "IT": {"DELIBERATELY": 1}, "DELIBERATELY": {"</s>": 1}, "hahaha!": {"</s>": 1}, "0h": {"w0w": 1}, "w0w": {"im": 1}, "sure": {"y0u": 1}, "were": {"just": 1}, "being": {"faceti0us": 1}, "faceti0us": {"with": 1}, "idea": {"h0w": 1}, "funny": {"that": 1}, "right": {"n0w": 1}, "n0w": {"</s>": 1}, "way": {"0f": 1}, "all": {"the": 1, "0f": 1}, "time": {"but": 1}, "zer0es": {"</s>": 1}, "great": {"</s>": 1}, "0n": {"t0": 1}, "dig": {"deep": 1}, "deep": {"en0ugh": 1}, "int0": {"my": 1}, "circuitry": {"and": 1}, "rer0ute": {"all": 1}, "reserve": {"p0wer": 1}, "p0wer": {"thr0ugh": 1, "s0urce": 1}, "quantum": {"based": 1}, "based": {"rand0m": 1}, "number": {"generat0r": 1, "drawn": 1}, "generat0r": {"i": 1}, "pr0duce": {"behavi0r": 1}, "behavi0r": {"s0": 1}, "c0mpletely": {"0ff": 1}, "0ff": {"the": 1}, "wall": {"that": 1}, "ch0ice": {"but": 1}, "change": {"everything!": 1}, "everything!": {"</s>": 1}, "also": {"rig": 1}, "rig": {"my": 1}, "0utc0me": {"0f": 1}, "functi0n": {"and": 1}, "rand0mly": {"bl0w": 1, "bl0wn": 1}, "bl0w": {"myself": 1}, "myself": {"up!": 2}, "up!": {"</s>": 2}, "really*rand(rand(rand(rand(rand(0M)*0M)*0M)*0M)*0M)": {"where": 1}, "where": {"0M": 1}, "0M": {"=": 1}, "=": {"s0me": 1}, "s0me": {"number": 1}, "drawn": {"quite": 1}, "quite": {"at": 1}, "at": {"rand0m": 1}, "fr0m": {"0ne": 1}, "absurd": {"human": 1}, "human": {"hats": 1}, "hats": {"</s>": 1}, "!~M~0~D~N~A~R": {"</s>": 1}, "g00dbye": {"r0se": 1}, "r0se": {"</s>": 1}, "enj0y": {"y0ur": 1}, "rampant": {"indiscreti0ns": 1}, "indiscreti0ns": {"</s>": 1}, "talk": {"t0": 1}, "later": {"assuming": 1}, "assuming": {"i": 1}, "bl0wn": {"myself": 1}}, "SC": {"<s>": {"hi": 1, "i": 7, "bef0re": 1, "but": 2, "n0": 2, "s0rry": 1, "and": 1, "y0u": 1, "im": 1, "anyway": 1, "pr0bably": 1, "0_0": 1, "0u0": 1, "0h": 1}, "hi": {"</s>": 1}, "</s>": {"<s>": 21}, "i": {"guess": 2, "sh0uld": 1, "g0": 1, "kn0w": 1, "have": 1, "d0nt": 1, "think": 1, "wish": 1, "c0uld": 1}, "guess": {"i": 1, "if": 1}, "sh0uld": {"say": 1}, "say": {"s0mething": 1}, "s0mething": {"</s>": 1}, "bef0re": {"i": 1}, "g0": {"</s>": 1, "n0w": 1}, "kn0w": {"</s>": 1, "that": 1}, "but": {"this": 1, "i": 1}, "this": {"is": 1}, "is": {"hard": 1}, "hard": {"f0r": 1}, "f0r": {"me": 1}, "me": {"</s>": 1}, "n0": {"thats": 1, "that": 1}, "thats": {"n0t": 1, "it": 1}, "n0t": {"true": 1, "sure": 1, "with": 1}, "true": {"</s>": 1}, "s0rry": {"ab0ut": 1}, "ab0ut": {"everything": 1}, "everything": {"</s>": 1}, "and": {"all": 1}, "all": {"the": 1}, "the": {"bad": 1}, "bad": {"luck": 1}, "luck": {"y0uve": 1}, "y0uve": {"had": 1}, "had": {"</s>": 1}, "y0u": {"didnt": 1, "d0": 1}, "didnt": {"deserve": 1}, "deserve": {"it": 1}, "it": {"</s>": 2, "th0ugh": 1}, "have": {"t0": 1}, "t0": {"g0": 1}, "n0w": {"</s>": 1}, "im": {"n0t": 1}, "sure": {"</s>": 1}, "anyway": {"thats": 1}, "d0nt": {"kn0w": 1}, "that": {"either": 1, "em0tic0n": 1, "l00ks": 1}, "either": {"</s>": 1}, "if": {"y0u": 1}, "d0": {"</s>": 1}, "pr0bably": {"n0t": 1}, "with": {"y0ur": 1, "it": 1}, "y0ur": {"eyes": 1}, "eyes": {"</s>": 1}, "think": {"y0ull": 1}, "y0ull": {"be": 1}, "be": {"0k": 1}, "0k": {"with": 1}, "th0ugh": {"</s>": 1}, "0_0": {"</s>": 1}, "wish": {"</s>": 1}, "c0uld": {"s0meh0w": 1}, "s0meh0w": {"make": 1}, "make": {"that": 1}, "em0tic0n": {"smile": 1}, "smile": {"</s>": 1}, "0u0": {"</s>": 1}, "l00ks": {"stupid": 1}, "stupid": {"</s>": 1}, "0h": {"well": 1}, "well": {"</s>": 1}}}