{"JE": {"<s>": {"hey": 1, "god": 1, "water": 2, ")(-EY": 1, "IM": 1, "yes": 2, "the": 1, "ok": 2, "be": 1, "which": 2, "im": 3, "now": 3, "ive": 1, "its": 1, "sayin": 1, "ooooh": 1, "not": 1, "who": 1, "werent": 1, "do": 1, "i": 3, "what": 1, "so": 3, "for": 1, "halibut": 1, "holy": 1, "well": 1, "maybe": 1, "this": 1, "right": 1, "I": 1, "hahahaha": 1, "excited": 1, "flippin": 1, "-EXCIT------ED": 1, "beacause": 1, "it": 1, "why": 1, "pretty": 1, "way": 1, "youre": 1, "whoever": 1, "nerd": 1, "she": 1, "dont": 1, "shes": 1, "ever": 1, "then": 1, "you": 1, "S-E--------------------E": 1, "better": 1, "(dream": 1, "(you": 2, "(gotch": 1, "(just": 1, "(biding": 1, "(gonna": 1, "(my": 2, "(call": 1, "(fishmael)": 1, "3B|": 1}, "hey": {"you": 1}, "you": {"</s>": 2, "doin": 1, "see": 1, "to": 1, "are": 1, "can": 1, "mention": 1, "somefin": 1, "were": 1, "demons": 1, "ask": 1, "know": 1, "do": 1, "stick": 1, "til": 1}, "</s>": {"<s>": 74}, "god": {"tier": 1}, "tier": {"boy": 1}, "boy": {"</s>": 2}, "water": {"you": 2}, "doin": {"there": 1}, "there": {"blue": 1, "and": 1}, "blue": {"boy": 1, "nerd)": 1}, ")(-EY": {"</s>": 1}, "IM": {"TALKING": 1}, "TALKING": {"TO": 1}, "TO": {"YOU": 1}, "YOU": {"</s>": 1}, "yes": {"you": 1, "</s>": 1}, "the": {"dork": 1, "pajamas": 1, "OT)(-ER": 1, "best": 1, "fuck": 1, "halibut": 1, "afterlife": 1, "girl": 1}, "dork": {"in": 2, "like": 1}, "in": {"the": 1, "pajamas": 1, "here": 1, "that": 1, "it": 1, "my": 1}, "pajamas": {"</s>": 2}, "ok": {"the": 1, "that": 1}, "OT)(-ER": {"dork": 1}, "be": {"all": 1}, "all": {"a": 1}, "a": {"pajama": 1, "whale": 1, "fish": 1, "good": 1, "fucking": 1, "hornless": 1, "couple": 1, "fork": 1}, "pajama": {"party": 1}, "party": {"up": 1}, "up": {"in": 1}, "here": {"today": 1, "</s>": 1}, "today": {"</s>": 1}, "which": {"troll": 1, "means": 1}, "troll": {"am": 1, "dummy": 1}, "am": {"i": 1, "pretty": 1}, "i": {"</s>": 1, "do": 1, "never": 1, "was": 1, "thought": 1, "told": 1, "am": 1, "tell": 1, "know": 1, "want)": 1}, "im": {"the": 1, "D-EAD": 1, "curious": 1}, "best": {"troll": 1}, "dummy": {"</s>": 1}, "now": {"get": 1, "</s>": 1, "beat": 1, "that": 1}, "get": {"away": 1}, "away": {"from": 1}, "from": {"her": 1}, "her": {"she": 1, "for": 1}, "she": {"is": 3, "like": 1}, "is": {"mine": 1, "obviously": 1, "the": 1, "but": 1, "</s>": 1}, "mine": {"</s>": 1, "if": 1}, "ive": {"been": 1}, "been": {"hunting": 1}, "hunting": {"her": 1}, "for": {"a": 1, "the": 1}, "whale": {"now": 1}, "its": {"a": 1}, "fish": {"pun": 1, "puns": 1}, "pun": {"</s>": 1}, "sayin": {"fish": 1}, "puns": {"is": 1}, "obviously": {"kind": 1}, "kind": {"of": 1}, "of": {"this": 1, "mine": 1, "em": 1, "it": 1, "freaks": 1, "an": 1, "whales)": 1, "dicks)": 1}, "this": {"thing": 1, "golden": 1, "is": 1}, "thing": {"i": 1}, "do": {"stupid": 1, "you": 1, "any": 1, "with": 1}, "stupid": {"G-ET": 1, "</s>": 1}, "G-ET": {"WIT)(": 1}, "WIT)(": {"T)(-E": 1}, "T)(-E": {"PROGRAM": 1}, "PROGRAM": {"</s>": 1}, "ooooh": {"thats": 1}, "thats": {"a": 1, "done": 1}, "good": {"one": 1}, "one": {"</s>": 1, "wasnt": 1}, "not": {"</s>": 1, "gonna": 1}, "beat": {"it": 1}, "it": {"</s>": 5, "to": 1, "means": 1}, "who": {"the": 1, "she": 1}, "fuck": {"are": 1}, "are": {"they": 1, "a": 1, "my": 1}, "they": {"</s>": 1}, "werent": {"no": 1}, "no": {"friends": 1}, "friends": {"of": 1}, "if": {"i": 1, "youre": 1, "you": 1}, "never": {"heard": 1}, "heard": {"of": 2}, "em": {"</s>": 1}, "see": {"this": 1, "</s>": 1}, "golden": {"pointy": 1}, "pointy": {"deal": 1}, "deal": {"here": 1}, "was": {"gonna": 1}, "gonna": {"use": 1, "go": 1}, "use": {"it": 1}, "to": {"poke": 1, "clamscray": 1, "welcome": 1, "hell": 1}, "poke": {"some": 1}, "some": {"holes": 1}, "holes": {"in": 1}, "that": {"girl": 1, "one": 1, "awesome": 1, "you": 1, "</s>": 1}, "girl": {"there": 1, "</s>": 1}, "and": {"see": 1, "stupid": 1, "biding)": 1}, "what": {"happens": 1, "you": 1}, "happens": {"</s>": 1}, "so": {"clamscray": 1, "like": 1, "the": 1}, "clamscray": {"</s>": 2}, "halibut": {"</s>": 1, "hell": 1}, "hell": {"of": 1, "</s>": 1}, "wasnt": {"that": 1}, "awesome": {"</s>": 1}, "thought": {"i": 1}, "told": {"you": 1}, "holy": {"mother": 1}, "mother": {"glubbing": 1}, "glubbing": {"mackerel": 1}, "mackerel": {"you": 1}, "fucking": {"idiot": 1}, "idiot": {"</s>": 1}, "well": {"if": 1}, "youre": {"not": 1, "dead": 1}, "go": {"</s>": 1}, "maybe": {"you": 1}, "can": {"at": 1}, "at": {"least": 1}, "least": {"tell": 1}, "tell": {"me": 1, "a": 1}, "me": {"somefin": 1, "to": 1, "</s>": 1}, "somefin": {"</s>": 2, "like": 1, "thats": 1}, "afterlife": {"isnt": 1}, "isnt": {"it": 1}, "means": {"</s>": 1, "my": 1}, "D-EAD": {"</s>": 1}, "right": {"</s>": 1, "where": 1}, "I": {"KN-EW": 1}, "KN-EW": {"IT": 1}, "IT": {"</s>": 1}, "hahahaha": {"yessssss": 1}, "yessssss": {"</s>": 1}, "excited": {"hmm": 1}, "hmm": {"</s>": 1}, "mention": {"it": 1}, "pretty": {"</s>": 1, "lame": 1}, "flippin": {"</s>": 1}, "-EXCIT------ED": {"</s>": 1}, "beacause": {"</s>": 1}, "my": {"plan": 1, "crosshairs": 1, "time)": 1, "obsession": 1}, "plan": {"worked": 1}, "worked": {"</s>": 1}, "why": {"would": 1, "a": 1}, "would": {"i": 1}, "hornless": {"dork": 1}, "like": {"you": 2, "that": 1, "</s>": 1, "your": 1}, "curious": {"about": 1}, "about": {"why": 1}, "couple": {"of": 1}, "freaks": {"like": 1}, "were": {"sent": 1}, "sent": {"to": 1}, "welcome": {"me": 1}, "demons": {"or": 1, "if": 1}, "or": {"somefin": 1, "whatever": 1}, "lame": {"demons": 1}, "ask": {"me": 1}, "way": {"too": 1}, "too": {"frondly": 1}, "frondly": {"and": 1}, "dead": {"aliens": 1}, "aliens": {"huh": 1}, "huh": {"</s>": 1}, "whoever": {"heard": 1}, "an": {"alien": 1}, "alien": {"ghost": 1}, "ghost": {"</s>": 1}, "nerd": {"</s>": 2}, "your": {"matesprit": 1}, "matesprit": {"or": 1}, "whatever": {"</s>": 1}, "dont": {"know": 1}, "know": {"who": 1, "W)(AT": 1, "-EXACTLY": 1}, "but": {"i": 1}, "W)(AT": {"she": 1}, "shes": {"done": 1}, "done": {"</s>": 2}, "ever": {"do": 1}, "any": {"baking": 1}, "baking": {"nerd": 1}, "then": {"you": 1}, "-EXACTLY": {"what": 1}, "with": {"somefin": 1}, "stick": {"a": 1}, "fork": {"in": 1}, "S-E--------------------E": {"</s>": 1}, "better": {"think": 1}, "think": {"fast": 1}, "fast": {"suckafish": 1}, "suckafish": {"</s>": 1}, "(dream": {"on": 1}, "on": {"blue": 1}, "nerd)": {"</s>": 1}, "(you": {"in": 1, "are": 1}, "crosshairs": {"sucka)": 1}, "sucka)": {"</s>": 1}, "(gotch": {"u": 1}, "u": {"right": 1}, "where": {"i": 1}, "want)": {"</s>": 1}, "(just": {"biding": 1}, "biding": {"my": 1}, "time)": {"</s>": 1}, "(biding": {"and": 1}, "biding)": {"</s>": 1}, "(gonna": {"hunt": 1}, "hunt": {"you": 1}, "til": {"we": 1}, "we": {"both": 1}, "both": {"double": 1}, "double": {"dead)": 1}, "dead)": {"</s>": 1}, "obsession": {"lil": 1}, "lil": {"bluefish)": 1}, "bluefish)": {"</s>": 1}, "(my": {"shrimpiest": 1, "mobiest": 1}, "shrimpiest": {"of": 1}, "whales)": {"</s>": 1}, "mobiest": {"of": 1}, "dicks)": {"</s>": 1}, "(call": {"me)": 1}, "me)": {"</s>": 1}, "(fishmael)": {"</s>": 1}, "3B|": {"</s>": 1}}, "AV": {"<s>": {"yea": 1, "um": 2, "god": 1, "pretty": 1, "...": 1, "dammit": 1, "you": 4, "mhm": 1, "shruggin": 1, "(floundering)": 1, "stop": 1, "dunno": 1, "thats": 4, "but": 6, "tempurarily?": 1, "na": 1, "haha": 1, "i": 11, "sea": 1, "and": 7, "guess": 1, "not": 2, "araneas": 1, "what": 2, "the": 1, "its": 2, "did": 1, "meant": 1, "then": 2, "mistakes": 1, "ya": 1, "ok": 1, "glub": 1, "feel": 1, "word": 1, "well": 2, "we": 1, "why": 3, "march": 1, "she": 3, "cant": 1, "who": 1, "that": 4, "tales": 1, "im": 1, "so": 2, "38(": 1, "makes": 1, "like": 2, "sneak": 1, "kay": 1, "gave": 1, "sure": 1, "it": 1, "if": 1, "nofin": 1, "hell": 1, "one": 1, "fuck": 1, "ran": 1, "iunno": 1, "nah": 1, "shell": 1, "be": 1, "of": 1, "makin": 1, "just": 1}, "yea": {"fraid": 1}, "fraid": {"so": 1}, "so": {"</s>": 1, "bad": 1, "i": 1, "we": 1}, "</s>": {"<s>": 108}, "um": {"no": 1, "</s>": 1}, "no": {"serk": 1}, "serk": {"its": 1, "</s>": 1}, "its": {"actually": 1, "supposed": 1, "about": 1, "a": 1}, "actually": {"a": 1, "doing": 1}, "a": {"real": 1, "pirate": 1, "flip": 1, "dumb": 1, "mistake": 1, "tide": 1, "shame": 1, "fish": 1, "crack": 1, "good": 1, "couple": 1, "fork": 1, "shit": 1, "made": 1, "dope": 1}, "real": {"thing": 1, "</s>": 2}, "thing": {"</s>": 1, "is": 1, "that": 1}, "god": {"damn": 1}, "damn": {"for": 1, "</s>": 1}, "for": {"a": 1, "me": 1, "T)(AT": 1, "her": 2, "anyone": 1}, "pirate": {"you": 1, "chick": 1, "who": 1}, "you": {"really": 1, "sure": 2, "fuckin": 1, "and": 1, "call": 1, "could": 1, "</s>": 2, "axed": 1, "bust": 1, "were": 1, "ask": 1, "aint": 2, "miserable": 1, "38)": 1}, "really": {"know": 1, "gives": 1, "connect": 1}, "know": {"fuckall": 1, "maybe??": 1}, "fuckall": {"about": 1}, "about": {"nautical": 1, "the": 1, "what": 1, "decisions": 1, "going": 1, "that": 1, "hero": 1}, "nautical": {"junk": 1}, "junk": {"</s>": 1}, "pretty": {"embarrassing": 1}, "embarrassing": {"tbh": 1}, "tbh": {"</s>": 1}, "...": {"</s>": 1}, "dammit": {"</s>": 1}, "sure": {"</s>": 2, "everyone": 2, "we": 1}, "mhm": {"</s>": 1}, "shruggin": {"ma": 1}, "ma": {"shoulders": 1}, "shoulders": {"yo": 1}, "yo": {"</s>": 1}, "(floundering)": {"</s>": 1}, "stop": {"movin": 1}, "movin": {"around": 1}, "around": {"all": 1}, "all": {"angry": 1, "the": 1, "makin": 1, "that": 1, "action": 1}, "angry": {"</s>": 1}, "fuckin": {"me": 1, "well": 1}, "me": {"up": 1, "</s>": 3, "feel": 1, "with": 1, "just": 1, "too": 1, "if": 1, "down": 1, "reel": 1}, "up": {"here": 1, "another": 1, "</s>": 3, "on": 1, "religious": 1}, "here": {"</s>": 2}, "dunno": {"wasnt": 1}, "wasnt": {"there": 1}, "there": {"</s>": 1}, "thats": {"some": 1, "what": 2, "not": 1, "a": 1, "how": 1}, "some": {"baller": 1, "mistakes": 1, "way": 1}, "baller": {"inward": 1}, "inward": {"reflection": 1}, "reflection": {"serk": 1}, "what": {"its": 1, "shes": 1, "those": 1, "they": 1, "you": 1, "can": 1, "if": 1}, "supposed": {"to": 1}, "to": {"do": 2, "english": 1, "fault": 1, "be": 2, "talk": 1, "teleport": 1, "him": 1, "the": 1}, "do": {"i": 1, "</s>": 1, "the": 1, "whatev": 1, "that": 1}, "i": {"think": 3, "dont": 3, "made": 1, "rolled": 1, "just": 1, "did": 1, "guess": 2, "will": 1, "always": 1, "give": 1, "hear": 1, "say": 1, "to": 1, "wanted": 1, "legit": 1, "didnt": 2, "found": 1, "beat": 1, "mean": 2, "thought": 1, "ever": 1, "said": 1, "wouldnt": 1}, "think": {"</s>": 1, "her": 1, "my": 1}, "but": {"like": 1, "who": 1, "thats": 1, "dumbass": 1, "then": 1, "yeah": 1, "i": 1, "hey": 1, "that": 1}, "like": {"</s>": 1, "all": 1, "you": 1, "glub": 1, "uh": 1, "pulling": 1, "that": 1}, "tempurarily?": {"</s>": 1}, "na": {"</s>": 1}, "haha": {"</s>": 1}, "dont": {"know": 1, "verbally": 1, "really": 1, "we": 1, "mean": 1}, "maybe??": {"</s>": 1}, "sea": {"my": 1}, "my": {"thing": 1, "cray": 1, "shelf": 1, "adult": 1, "wrestling": 1}, "is": {"</s>": 2, "never": 1, "cause": 1, "ridic": 1}, "verbally": {"torture": 1}, "torture": {"my": 1}, "cray": {"schemes": 1}, "schemes": {"like": 1}, "the": {"serket": 1, "stuff": 1, "things": 2, "source": 1, "shit": 4, "lake": 1, "pirate": 1, "best": 2, "plan": 1, "weapon": 1, "scenery": 1, "moon": 1, "religious": 1, "general": 1}, "serket": {"girls": 1}, "girls": {"</s>": 1}, "and": {"that": 2, "she": 1, "makin": 1, "above": 1, "the": 1, "if": 2, "oh": 1, "start": 1, "i": 1, "kinda": 1, "ruthlessly": 1}, "that": {"works": 1, "critical": 1, "shit": 2, "sucked": 1, "</s>": 3, "journal": 1, "dont": 1, "just": 2, "was": 1, "aint": 1, "id": 1}, "works": {"ok": 1, "out": 1}, "ok": {"for": 1, "i": 1}, "guess": {"i": 1, "thats": 1, "</s>": 1}, "made": {"some": 1, "involved": 1, "up": 1}, "mistakes": {"but": 1, "aint": 1}, "who": {"really": 1, "am": 1, "wont": 1, "wanna": 1}, "gives": {"a": 1}, "flip": {"</s>": 1}, "not": {"like": 1, "how": 1, "</s>": 1, "one": 1, "that": 1}, "she": {"do": 1, "always": 1, "does": 1, "is": 1, "ditched": 1, "wanna": 1, "cast": 1}, "araneas": {"deal": 1}, "deal": {"is": 1}, "shes": {"doin": 1, "actually": 1, "obviously": 1}, "doin": {"now": 1}, "now": {"isnt": 1}, "isnt": {"much": 1}, "much": {"different": 1}, "different": {"from": 1}, "from": {"how": 1, "the": 1}, "how": {"she": 1, "important": 1, "i": 1, "this": 1}, "always": {"did": 1, "felt": 1}, "did": {"stuff": 1, "shit": 1, "</s>": 1, "it": 1}, "stuff": {"</s>": 1, "she": 1}, "does": {"is": 1}, "never": {"about": 1}, "things": {"shes": 1, "M-EAN": 1, "the": 1}, "doing": {"</s>": 1}, "those": {"things": 1, "delusions": 1}, "M-EAN": {"and": 1}, "makin": {"sure": 2, "it": 1}, "everyone": {"KNOWS": 1, "understands": 1}, "KNOWS": {"what": 1}, "they": {"mean": 1}, "mean": {"</s>": 2, "i": 1, "yeah": 1}, "above": {"all": 1}, "understands": {"how": 1}, "important": {"she": 1}, "cause": {"shes": 1}, "obviously": {"the": 1}, "source": {"of": 1}, "of": {"all": 1, "cute": 1, "him": 1, "cowards": 1, "met": 1, "course": 1}, "critical": {"M-EANING": 1}, "M-EANING": {"without": 1}, "without": {"which": 1, "her": 2}, "which": {"all": 1}, "action": {"would": 1}, "would": {"be": 2, "i": 1}, "be": {"pointless": 1, "dat": 1, "lochness": 1, "the": 1, "like": 1, "</s>": 1, "fake": 1}, "pointless": {"right?": 1}, "right?": {"</s>": 1}, "rolled": {"</s>": 1}, "just": {"</s>": 2, "thinkin": 1, "do": 1, "makes": 1, "saying": 1}, "shit": {"</s>": 2, "i": 1, "accomplished": 2, "without": 1, "out": 1, "idea": 1, "aint": 1}, "meant": {"only": 1}, "only": {"the": 1}, "accomplished": {"</s>": 1, "a": 1}, "if": {"that": 1, "you": 3, "i": 2, "</s>": 1, "a": 1}, "dumb": {"thing": 1}, "sucked": {"</s>": 1}, "then": {"i": 1, "</s>": 1, "you": 1}, "call": {"a": 1}, "mistake": {"and": 1}, "oh": {"fuckin": 1}, "well": {"</s>": 2, "yeah": 1}, "aint": {"make": 1, "feelin": 2, "us": 1, "real": 1}, "make": {"me": 1}, "feel": {"too": 1, "me": 1, "a": 1}, "too": {"bad": 1, "</s>": 1}, "bad": {"since": 1, "about": 1, "</s>": 1}, "since": {"i": 1}, "connect": {"results": 1}, "results": {"with": 1}, "with": {"my": 2, "less": 1, "you": 1, "stickin": 1, "a": 1}, "shelf": {"worth": 1}, "worth": {"</s>": 1}, "ya": {"feel": 1}, "will": {"admit": 1}, "admit": {"</s>": 1}, "felt": {"hella": 1}, "hella": {"bad": 1}, "decisions": {"leavin": 1}, "leavin": {"me": 1}, "less": {"gold": 1}, "gold": {"</s>": 1}, "glub": {"damn": 1, "yes": 1}, "tide": {"a": 1}, "shame": {"wash": 1}, "wash": {"over": 1}, "over": {"me": 1, "to": 1, "flipper": 1}, "thinkin": {"about": 1}, "going": {"broke": 1}, "broke": {"</s>": 1}, "word": {"</s>": 1}, "we": {"still": 1, "just": 1, "cant": 1, "cool": 1}, "still": {"have": 1}, "have": {"this": 1}, "this": {"treasure": 1, "whole": 1}, "treasure": {"here": 1}, "why": {"dont": 1, "not": 1, "would": 1}, "her": {"</s>": 3, "i": 1, "piratesona": 1, "lure": 1, "mindfang": 1, "job": 1, "own": 1}, "could": {"whip": 1}, "whip": {"up": 1}, "another": {"ghost": 1}, "ghost": {"army": 1}, "army": {"</s>": 1}, "march": {"it": 1}, "it": {"strait": 1, "works": 1, "was": 1, "you": 1, "</s>": 2, "would": 1, "convenient": 1}, "strait": {"to": 1}, "english": {"and": 1}, "start": {"beatin": 1}, "beatin": {"him": 1}, "him": {"down": 1, "</s>": 1, "with": 1}, "down": {"</s>": 1, "for": 1}, "give": {"a": 1}, "fish": {"about": 1}, "hear": {"you": 1}, "ditched": {"me": 1, "</s>": 1}, "cant": {"blame": 1, "salvage": 1}, "blame": {"her": 1}, "can": {"i": 1}, "say": {"girl": 1}, "girl": {"loves": 1}, "loves": {"her": 1}, "piratesona": {"</s>": 1}, "wanna": {"be": 1, "exploit": 1}, "dat": {"pirate": 1}, "chick": {"so": 1}, "am": {"i": 1}, "fault": {"ambition": 1}, "ambition": {"</s>": 1}, "cast": {"her": 1}, "lure": {"into": 1}, "into": {"the": 1}, "lake": {"of": 1}, "cute": {"but": 1}, "dumbass": {"dreams": 1}, "dreams": {"</s>": 1}, "mindfang": {"ideal": 1}, "ideal": {"is": 1}, "ridic": {"to": 1}, "lochness": {"with": 1}, "journal": {"man": 1}, "man": {"</s>": 1}, "tales": {"from": 1}, "wont": {"shut": 1}, "shut": {"up": 1}, "im": {"not": 1}, "one": {"to": 1, "day": 1}, "talk": {"about": 1}, "hero": {"worship": 1}, "worship": {"</s>": 1}, "adult": {"self": 1}, "self": {"happens": 1}, "happens": {"to": 1}, "best": {"best": 1, "greatest": 1, "choice": 1}, "greatest": {"most": 1}, "most": {"perfect": 1}, "perfect": {"beautiful": 1}, "beautiful": {"woman": 1}, "woman": {"-----EV-----ER": 1}, "-----EV-----ER": {"an": 1}, "an": {"if": 1, "being": 1}, "axed": {"me": 1}, "wanted": {"a": 1}, "crack": {"at": 1}, "at": {"her": 1}, "job": {"id": 1}, "id": {"be": 1, "ever": 1}, "yes": {"put": 1, "</s>": 1}, "put": {"me": 1}, "T)(AT": {"</s>": 1}, "legit": {"hope": 1}, "hope": {"it": 1}, "out": {"for": 1, "of": 1, "the": 1, "by": 1}, "yeah": {"</s>": 2, "you": 1}, "didnt": {"get": 1, "do": 1}, "get": {"ditched": 1}, "38(": {"</s>": 1}, "makes": {"me": 1, "you": 1}, "reel": {"sad": 1}, "sad": {"</s>": 1}, "salvage": {"the": 1}, "plan": {"without": 1}, "uh": {"</s>": 1}, "sneak": {"up": 1}, "on": {"him?": 1}, "him?": {"</s>": 1}, "kay": {"what": 1}, "found": {"some": 1}, "way": {"to": 1}, "teleport": {"over": 1}, "beat": {"the": 1}, "wrestling": {"moves": 1}, "moves": {"</s>": 1}, "bust": {"out": 1}, "weapon": {"</s>": 1}, "was": {"badass": 1, "cool": 1}, "badass": {"though": 1, "objectives": 1}, "though": {"</s>": 1}, "were": {"chewin": 1}, "chewin": {"the": 1}, "scenery": {"an": 1}, "being": {"hammy": 1}, "hammy": {"as": 1}, "as": {"fuck": 1, "shit": 1}, "fuck": {"but": 1, "da": 1}, "thought": {"it": 1}, "cool": {"and": 1, "to": 1}, "kinda": {"funny": 1}, "funny": {"</s>": 1}, "good": {"enough": 1}, "enough": {"reason": 1}, "reason": {"if": 1}, "ask": {"me": 1}, "hey": {"if": 1}, "feelin": {"it": 2}, "gave": {"up": 1}, "couple": {"of": 1}, "cowards": {"did": 1}, "us": {"</s>": 1}, "whatev": {"</s>": 1}, "nofin": {"wrong": 1}, "wrong": {"with": 1}, "stickin": {"a": 1}, "fork": {"in": 1}, "in": {"a": 1, "clams": 1}, "idea": {"that": 1}, "miserable": {"</s>": 1}, "hell": {"the": 1}, "choice": {"i": 1}, "ever": {"made": 1, "bother": 1}, "involved": {"givin": 1}, "givin": {"up": 1}, "day": {"i": 1}, "said": {"</s>": 1}, "da": {"throne": 1}, "throne": {"</s>": 1}, "ran": {"off": 1}, "off": {"to": 1, "</s>": 1}, "moon": {"</s>": 1}, "whole": {"crazy": 1}, "crazy": {"mess": 1}, "mess": {"kicked": 1}, "kicked": {"off": 1}, "wouldnt": {"of": 1}, "met": {"you": 1}, "38)": {"</s>": 1}, "iunno": {"</s>": 1}, "nah": {"</s>": 1}, "religious": {"belief": 1, "beliefs": 1}, "belief": {"pimped": 1}, "pimped": {"out": 1}, "by": {"trash": 1}, "trash": {"clowns": 1}, "clowns": {"</s>": 1}, "shell": {"yes": 1}, "fake": {"as": 1}, "course": {"the": 1}, "beliefs": {"themselves": 1}, "themselves": {"are": 1}, "are": {"real": 1}, "convenient": {"for": 1}, "anyone": {"who": 1}, "exploit": {"those": 1}, "delusions": {"for": 1}, "own": {"badass": 1}, "objectives": {"</s>": 1}, "pulling": {"in": 1}, "clams": {"hand": 1}, "hand": {"over": 1}, "flipper": {"and": 1}, "ruthlessly": {"subjugating": 1}, "subjugating": {"the": 1}, "general": {"public": 1}, "public": {"</s>": 1}, "bother": {"with": 1}, "dope": {"scheme": 1}, "scheme": {"like": 1}, "saying": {"</s>": 1}}, "AM": {"<s>": {"(wut)": 1}, "(wut)": {"</s>": 1}}, "KV": {"<s>": {"nubs": 1, "come": 1, "do": 1, "shouty": 2, "yeh": 1, "we": 1}, "nubs": {"mcshouty": 1}, "mcshouty": {"</s>": 1}, "</s>": {"<s>": 6}, "come": {"in": 1}, "in": {"shouty": 1}, "shouty": {"</s>": 1, "is": 1, "stfu": 1}, "do": {"you": 1}, "you": {"read": 1, "</s>": 1}, "read": {"me": 1}, "me": {"</s>": 1}, "is": {"that": 1}, "that": {"you": 1}, "yeh": {"</s>": 1}, "stfu": {"</s>": 1}, "we": {"got": 1}, "got": {"a": 1}, "a": {"whale": 1, "problem": 1}, "whale": {"of": 1}, "of": {"a": 1}, "problem": {"here": 1}, "here": {"</s>": 1}}, "VS": {"<s>": {"i": 9, "lets": 1, "get": 1, "nice": 1, "how": 2, "god": 1, "got": 2, "na": 1, "spider": 1, "wat": 1, "ooh": 1, "man": 2, "T)(AT": 1, "yeah": 3, "much": 1, "thats": 1, "...": 1, ".........": 1, "hey": 1, "can": 1, "7.5": 1, "nofin": 1, "change": 1, "that": 4, "so": 4, "english": 1, "like": 1, "with": 1, "cartographic": 1, "im": 1, "we": 2, "well": 3, "but": 1, "aranea": 1, "she": 2, "the": 1, "tryin": 1, "basically": 1, "and": 4, "mellowed": 1, "which": 2, "k": 1, "reely": 1, "uh": 1, "in": 1, "you": 2, "oh": 1, "yeah...": 1, "afaik": 1, "guess": 1, "dunno": 1, "it": 1, "apparently": 1, "then": 1, "aight": 1, "nope": 1, "true": 1, "do": 1, "know": 1, "yours": 1, "if": 1, "??": 1, "its": 1}, "i": {"just": 1, "can": 1, "aint": 1, "ask": 1, "mean": 3, "guess": 2, "stuck": 1, "didnt": 1, "ever": 1, "never": 2, "dont": 2, "pretty": 1, "was": 1, "make": 1, "saw": 1}, "just": {"did": 1, "</s>": 1, "me": 1, "gave": 1, "kept": 1, "forgot": 1}, "did": {"</s>": 2}, "</s>": {"<s>": 90}, "lets": {"just": 1}, "get": {"out": 1, "away": 1}, "out": {"of": 1, "and": 2, "what": 1, "</s>": 1}, "of": {"here": 1, "economics": 1, "fish": 1, "my": 1, "subject": 1, "that": 1, "grandeur": 1, "things": 1, "anyone": 1, "the": 3}, "here": {"ok": 1, "</s>": 1}, "ok": {"</s>": 1}, "nice": {"watch": 1}, "watch": {"dealie": 1}, "dealie": {"</s>": 1}, "how": {"much": 1, "old": 1, "but": 1, "long": 1}, "much": {"that": 1, "a": 1, "to": 1, "just": 1}, "that": {"worth": 1, "answer": 1, "personal": 1, "old": 1, "helped": 1, "weird": 1, "magic": 1, "left": 1, "</s>": 1, "\"lost": 1, "was": 2, "makes": 1, "made": 1, "weapon": 1, "shit": 1}, "worth": {"</s>": 1, "bothering": 1}, "god": {"dammit": 1}, "dammit": {"that": 1}, "answer": {"was": 1}, "was": {"too": 1, "trying": 1, "actually": 1, "like": 1, "a": 1, "one": 1, "even": 1, "mostly": 1, "towing": 1}, "too": {"complicated": 1}, "complicated": {"</s>": 1}, "got": {"a": 1, "to": 1, "the": 1, "uh": 1, "owned": 1}, "a": {"fuckin": 1, "storyteller": 1, "kinda": 1, "lil": 1, "damn": 1, "path": 1, "flying": 1, "treasure": 1, "while": 2, "bit": 1, "bogus": 1, "ghost": 1}, "fuckin": {"professor": 1, "sextants": 1, "m$ney": 1}, "professor": {"of": 1}, "economics": {"over": 1}, "over": {"here": 1}, "na": {"serk": 1}, "serk": {"</s>": 2, "38)": 1}, "spider": {"swag": 1}, "swag": {"aint": 1}, "aint": {"my": 1, "much": 1, "a": 1}, "my": {"kettle": 1, "former": 1}, "kettle": {"of": 1}, "fish": {"</s>": 1, "and": 1}, "wat": {"</s>": 1}, "ooh": {"right": 1}, "right": {"</s>": 1}, "man": {"</s>": 2}, "T)(AT": {"old": 1}, "old": {"thing": 1, "are": 1, "ass": 1}, "thing": {"</s>": 1}, "yeah": {"i": 1, "we": 1, "im": 1, "that": 1}, "can": {"debrief": 1, "i": 1}, "debrief": {"</s>": 1}, "storyteller": {"tho": 1}, "tho": {"</s>": 1}, "to": {"the": 2, "her": 1, "do": 3, "</s>": 1, "figure": 1, "tell": 1}, "the": {"lament": 1, "top": 1, "ring": 2, "treasure": 2, "crew": 1, "delusions": 1, "most": 1, "plan": 2, "fuck": 1, "thump": 1, "whole": 2, "things": 1, "load": 1, "hell": 1}, "lament": {"of": 1}, "former": {"bestie": 1}, "bestie": {"</s>": 1}, "thats": {"why": 1, "a": 1, "bassically": 1, "everything": 1}, "why": {"youre": 1}, "youre": {"the": 1}, "top": {"serk": 1}, "38)": {"</s>": 1}, "...": {"</s>": 1}, ".........": {"</s>": 1}, "hey": {"</s>": 1}, "ask": {"a": 1}, "kinda": {"personal": 1, "goin": 1}, "personal": {"question": 1, "but": 1}, "question": {"</s>": 1}, "mean": {"not": 1, "she...": 1, "until": 1}, "not": {"even": 2}, "even": {"that": 1, "sure": 1, "know": 1, "worth": 1, "</s>": 1}, "but": {"whatev": 1, "that": 1, "you": 1, "also": 1, "true": 1}, "whatev": {"</s>": 1}, "are": {"you": 1}, "you": {"</s>": 3, "were": 1, "showed": 1, "made": 1, "even": 1, "say": 1, "roll": 1, "aint": 1, "cant": 1}, "7.5": {"huh": 1}, "huh": {"</s>": 1}, "guess": {"thats": 2, "it": 1}, "lil": {"more": 1}, "more": {"respectable": 1}, "respectable": {"</s>": 1}, "nofin": {"</s>": 1}, "change": {"of": 1}, "subject": {"</s>": 1}, "ass": {"mission...": 1, "idea": 1}, "mission...": {"</s>": 1}, "so": {"yeah": 1, "she": 1, "we": 1, "i": 1, "</s>": 2}, "we": {"all": 1, "found": 1, "couldnt": 1, "just": 2}, "all": {"piled": 1, "</s>": 1}, "piled": {"in": 1}, "in": {"a": 1, "this": 1, "whatever": 1, "fact": 1}, "damn": {"pirate": 1}, "pirate": {"ship": 1}, "ship": {"and": 1}, "and": {"sailed": 1, "wrecked": 1, "junk": 1, "scopes": 1, "fuckin": 1, "whatnot": 1, "driving": 1, "i": 1, "doing": 1, "stole": 1, "made": 1, "tbh": 1, "you": 1, "were": 1, "wandered": 1, "you...": 1, "thats": 1, "that": 1, "she": 1, "got": 1}, "sailed": {"around": 1}, "around": {"the": 1, "though": 1}, "ring": {"in": 1, "and": 1, "ganked": 1}, "this": {"huge": 1, "deadly": 1, "whole": 1}, "huge": {"circle": 1}, "circle": {"</s>": 1}, "english": {"followed": 1}, "followed": {"us": 1}, "us": {"and": 1, "chart": 1, "wonder": 1}, "wrecked": {"shit": 1}, "shit": {"as": 1, "</s>": 2, "for": 1}, "as": {"he": 1}, "he": {"went": 1}, "went": {"</s>": 1}, "helped": {"us": 1}, "chart": {"a": 1}, "path": {"to": 1}, "treasure": {"somehow": 1, "</s>": 2}, "somehow": {"</s>": 1}, "like": {"using": 1, "</s>": 2}, "using": {"black": 1}, "black": {"maps": 1}, "maps": {"and": 1}, "junk": {"</s>": 1}, "with": {"like": 1, "this": 1, "that": 1}, "cartographic": {"calculations": 1}, "calculations": {"and": 1}, "scopes": {"and": 1}, "sextants": {"and": 1}, "whatnot": {"</s>": 1}, "im": {"not": 1, "on": 1}, "sure": {"how": 1}, "weird": {"ass": 1}, "idea": {"actually": 1}, "actually": {"worked": 1, "sorta": 1}, "worked": {"</s>": 1}, "found": {"the": 1}, "well": {"YOU": 1, "OT)(-ER": 1, "fuck": 1}, "YOU": {"did": 1}, "were": {"also": 1, "feelin": 1}, "also": {"kinda": 1, "sorta...": 1}, "goin": {"nuts": 1}, "nuts": {"and": 1}, "driving": {"everyone": 1}, "everyone": {"away": 1}, "away": {"from": 1, "with": 1}, "from": {"the": 1, "her": 2}, "crew": {"</s>": 1}, "stuck": {"around": 1}, "though": {"cause": 1, "</s>": 2}, "cause": {"i": 1}, "didnt": {"give": 1}, "give": {"a": 1}, "flying": {"glub": 1}, "glub": {"</s>": 1}, "aranea": {"bailed": 1, "was": 1}, "bailed": {"though": 1}, "she": {"caught": 1, "ollied": 1, "totally": 1, "was": 1, "probably": 1, "peaced": 1}, "caught": {"wind": 1}, "wind": {"of": 1}, "magic": {"ring": 1}, "it": {"got": 1, "and": 1, "sound": 1, "was": 2}, "her": {"</s>": 1, "then": 1, "ever": 1, "though": 1}, "delusions": {"of": 1}, "grandeur": {"about": 1}, "about": {"being": 1, "the": 1}, "being": {"alive": 1}, "alive": {"again": 1}, "again": {"and": 1, "</s>": 1, "so": 1}, "doing": {"relevant": 1}, "relevant": {"shit": 1}, "ollied": {"out": 1}, "stole": {"it": 1}, "made": {"the": 1, "it": 1, "us": 1}, "most": {"embarrassing": 1, "of": 1}, "embarrassing": {"mess": 1}, "mess": {"of": 1}, "things": {"i": 1, "that": 1}, "ever": {"heard": 1, "</s>": 1, "since": 1}, "heard": {"of": 1, "from": 1}, "anyone": {"doin": 1}, "doin": {"ever": 1}, "totally": {"failed": 1}, "failed": {"in": 1}, "whatever": {"she": 1}, "trying": {"to": 1}, "do": {"</s>": 1, "with": 1, "other": 1, "you": 1}, "ganked": {"from": 1}, "then": {"died": 1, "she": 1}, "died": {"again": 1}, "never": {"saw": 1, "mind": 1, "had": 1}, "saw": {"or": 1, "you": 1}, "or": {"heard": 1}, "since": {"and": 1}, "tbh": {"i": 1}, "dont": {"really": 1, "even": 1, "matter": 1}, "really": {"want": 1}, "want": {"to": 1}, "left": {"just": 1}, "me": {"and": 1}, "OT)(-ER": {"you": 1}, "tryin": {"to": 1}, "figure": {"out": 1}, "what": {"to": 1, "that": 1}, "deadly": {"box": 1}, "box": {"a": 1}, "basically": {"we": 1}, "couldnt": {"decide": 1}, "decide": {"on": 1}, "on": {"anything": 1, "the": 1, "board": 1}, "anything": {"</s>": 1}, "feelin": {"pretty": 1}, "pretty": {"flat": 1, "much": 1, "cool": 1}, "flat": {"on": 1}, "plan": {"overall": 1, "until": 1, "</s>": 1}, "overall": {"</s>": 1}, "gave": {"up": 1}, "up": {"and": 1, "</s>": 1, "but": 1}, "wandered": {"off": 1}, "off": {"to": 1}, "other": {"shit": 1}, "for": {"a": 2, "i": 1}, "while": {"</s>": 1, "38\\": 1}, "you...": {"i": 1}, "she...": {"</s>": 1}, "mellowed": {"WAY": 1}, "WAY": {"the": 1}, "fuck": {"out": 1, "</s>": 1}, "which": {"was": 1, "got": 1}, "sorta": {"cool": 1}, "cool": {"for": 1, "again": 1}, "bit": {"but": 1}, "sorta...": {"</s>": 1}, "k": {"never": 1}, "mind": {"that": 1, "control": 1}, "kept": {"bubble": 1}, "bubble": {"hopping": 1}, "hopping": {"for": 1}, "know": {"how": 1, "what": 1}, "long": {"</s>": 1}, "uh": {"</s>": 1, "i": 1}, "reely": {"boring": 1}, "boring": {"after": 1}, "after": {"a": 1}, "38\\": {"</s>": 1}, "had": {"the": 1}, "thump": {"tortoise": 1}, "tortoise": {"to": 1}, "tell": {"her": 1}, "until": {"now": 1, "you": 1}, "now": {"</s>": 1}, "fact": {"i": 1}, "forgot": {"about": 1}, "whole": {"plan": 1, "story": 1, "mind": 1}, "showed": {"up": 1}, "sound": {"pretty": 1}, "board": {"</s>": 1}, "bassically": {"the": 1}, "story": {"</s>": 1}, "oh": {"</s>": 1}, "yeah...": {"</s>": 1}, "\"lost": {"cherub\"": 1}, "cherub\"": {"part": 1}, "part": {"of": 1}, "afaik": {"that": 1}, "bogus": {"red": 1}, "red": {"distraction": 1}, "distraction": {"fish": 1}, "probably": {"dont": 1}, "matter": {"at": 1}, "at": {"all": 1}, "everything": {"</s>": 1}, "makes": {"sense": 1}, "sense": {"</s>": 1}, "dunno": {"</s>": 1}, "one": {"of": 1}, "wonder": {"if": 1}, "if": {"it": 1, "you": 1}, "bothering": {"anymore": 1}, "anymore": {"</s>": 1}, "mostly": {"this": 1}, "control": {"stunt": 1}, "stunt": {"</s>": 1}, "apparently": {"aranea": 1}, "towing": {"most": 1}, "load": {"there???": 1}, "there???": {"</s>": 1}, "peaced": {"the": 1}, "hell": {"out": 1}, "owned": {"</s>": 1}, "aight": {"</s>": 1}, "nope": {"</s>": 1}, "true": {"</s>": 2}, "weapon": {"does": 1}, "does": {"yet": 1}, "yet": {"or...": 1}, "or...": {"</s>": 1}, "yours": {"</s>": 1}, "say": {"so": 1}, "make": {"fuckin": 1}, "m$ney": {"bitch": 1}, "bitch": {"</s>": 1}, "roll": {"them": 1}, "them": {"eyes": 1}, "eyes": {"serk": 1}, "ghost": {"you": 1}, "cant": {"get": 1}, "??": {"</s>": 1}, "its": {"fucked": 1}, "fucked": {"up": 1}}, "TN": {"<s>": {"yea": 1, "excellent": 1, "i": 2, "you": 1, "now": 1}, "yea": {"good": 1}, "good": {"</s>": 1}, "</s>": {"<s>": 5}, "excellent": {"work": 1}, "work": {"swabby": 1}, "swabby": {"in": 1}, "in": {"chief": 1}, "chief": {"</s>": 1}, "i": {"hereby": 1, "wanna": 1}, "hereby": {"promote": 1}, "promote": {"yall": 1}, "yall": {"from": 1}, "from": {"poopmaster": 1}, "poopmaster": {"to": 1}, "to": {"pooplord": 1}, "pooplord": {"</s>": 1}, "you": {"earned": 1}, "earned": {"it": 1}, "it": {"</s>": 1}, "now": {"turn": 1}, "turn": {"that": 1}, "that": {"way": 1}, "way": {"</s>": 1}, "wanna": {"address": 1}, "address": {"my": 1}, "my": {"legion": 1}, "legion": {"of": 1}, "of": {"loyal": 1}, "loyal": {"homies": 1}, "homies": {"</s>": 1}}}